{
    "joints": [
        {
            "orientation": {
                "v": [
                    0.43504664301872253,
                    0.5425362586975098,
                    -0.4987383782863617,
                    -0.5173478722572327
                ],
                "wxyz": {
                    "w": 0.43504664301872253,
                    "x": 0.5425362586975098,
                    "y": -0.4987383782863617,
                    "z": -0.5173478722572327
                }
            },
            "position": {
                "v": [
                    -27.1856689453125,
                    -164.52786254882813,
                    1649.6763916015625
                ],
                "xyz": {
                    "x": -27.1856689453125,
                    "y": -164.52786254882813,
                    "z": 1649.6763916015625
                }
            }
        },
        {
            "orientation": {
                "v": [
                    0.3914666771888733,
                    0.5813530087471008,
                    -0.4528954029083252,
                    -0.5510610938072205
                ],
                "wxyz": {
                    "w": 0.3914666771888733,
                    "x": 0.5813530087471008,
                    "y": -0.4528954029083252,
                    "z": -0.5510610938072205
                }
            },
            "position": {
                "v": [
                    -33.142940521240234,
                    -352.0617980957031,
                    1622.7598876953125
                ],
                "xyz": {
                    "x": -33.142940521240234,
                    "y": -352.0617980957031,
                    "z": 1622.7598876953125
                }
            }
        },
        {
            "orientation": {
                "v": [
                    0.316084623336792,
                    0.6216463446617126,
                    -0.4037770926952362,
                    -0.5921236276626587
                ],
                "wxyz": {
                    "w": 0.316084623336792,
                    "x": 0.6216463446617126,
                    "y": -0.4037770926952362,
                    "z": -0.5921236276626587
                }
            },
            "position": {
                "v": [
                    -35.804019927978516,
                    -497.23516845703125,
                    1579.393798828125
                ],
                "xyz": {
                    "x": -35.804019927978516,
                    "y": -497.23516845703125,
                    "z": 1579.393798828125
                }
            }
        },
        {
            "orientation": {
                "v": [
                    0.3625510036945343,
                    0.5872639417648315,
                    -0.45232856273651123,
                    -0.5648688077926636
                ],
                "wxyz": {
                    "w": 0.3625510036945343,
                    "x": 0.5872639417648315,
                    "y": -0.45232856273651123,
                    "z": -0.5648688077926636
                }
            },
            "position": {
                "v": [
                    -41.971839904785156,
                    -698.9003295898438,
                    1467.59033203125
                ],
                "xyz": {
                    "x": -41.971839904785156,
                    "y": -698.9003295898438,
                    "z": 1467.59033203125
                }
            }
        },
        {
            "orientation": {
                "v": [
                    -0.039187438786029816,
                    -0.18672792613506317,
                    0.5563992261886597,
                    0.8087131381034851
                ],
                "wxyz": {
                    "w": -0.039187438786029816,
                    "x": -0.18672792613506317,
                    "y": 0.5563992261886597,
                    "z": 0.8087131381034851
                }
            },
            "position": {
                "v": [
                    -76.31950378417969,
                    -662.273193359375,
                    1481.3980712890625
                ],
                "xyz": {
                    "x": -76.31950378417969,
                    "y": -662.273193359375,
                    "z": 1481.3980712890625
                }
            }
        },
        {
            "orientation": {
                "v": [
                    -0.3748275935649872,
                    0.21942926943302155,
                    0.14126834273338318,
                    0.889605700969696
                ],
                "wxyz": {
                    "w": -0.3748275935649872,
                    "x": 0.21942926943302155,
                    "y": 0.14126834273338318,
                    "z": 0.889605700969696
                }
            },
            "position": {
                "v": [
                    -217.14321899414063,
                    -703.4594116210938,
                    1442.1502685546875
                ],
                "xyz": {
                    "x": -217.14321899414063,
                    "y": -703.4594116210938,
                    "z": 1442.1502685546875
                }
            }
        },
        {
            "orientation": {
                "v": [
                    0.9511210918426514,
                    -0.23741598427295685,
                    0.10834956169128418,
                    -0.16511408984661102
                ],
                "wxyz": {
                    "w": 0.9511210918426514,
                    "x": -0.23741598427295685,
                    "y": 0.10834956169128418,
                    "z": -0.16511408984661102
                }
            },
            "position": {
                "v": [
                    -399.97308349609375,
                    -881.060302734375,
                    1587.86962890625
                ],
                "xyz": {
                    "x": -399.97308349609375,
                    "y": -881.060302734375,
                    "z": 1587.86962890625
                }
            }
        },
        {
            "orientation": {
                "v": [
                    0.8438811302185059,
                    -0.31580987572669983,
                    0.3940238952636719,
                    0.1813117265701294
                ],
                "wxyz": {
                    "w": 0.8438811302185059,
                    "x": -0.31580987572669983,
                    "y": 0.3940238952636719,
                    "z": 0.1813117265701294
                }
            },
            "position": {
                "v": [
                    -172.77133178710938,
                    -971.1367797851563,
                    1556.39990234375
                ],
                "xyz": {
                    "x": -172.77133178710938,
                    "y": -971.1367797851563,
                    "z": 1556.39990234375
                }
            }
        },
        {
            "orientation": {
                "v": [
                    0.82732093334198,
                    -0.2843731641769409,
                    0.4172799587249756,
                    0.24606801569461823
                ],
                "wxyz": {
                    "w": 0.82732093334198,
                    "x": -0.2843731641769409,
                    "y": 0.4172799587249756,
                    "z": 0.24606801569461823
                }
            },
            "position": {
                "v": [
                    -111.1583023071289,
                    -956.0977172851563,
                    1476.122314453125
                ],
                "xyz": {
                    "x": -111.1583023071289,
                    "y": -956.0977172851563,
                    "z": 1476.122314453125
                }
            }
        },
        {
            "orientation": {
                "v": [
                    0.82732093334198,
                    -0.2843731641769409,
                    0.4172799587249756,
                    0.24606801569461823
                ],
                "wxyz": {
                    "w": 0.82732093334198,
                    "x": -0.2843731641769409,
                    "y": 0.4172799587249756,
                    "z": 0.24606801569461823
                }
            },
            "position": {
                "v": [
                    -50.23699951171875,
                    -936.6008911132813,
                    1380.7894287109375
                ],
                "xyz": {
                    "x": -50.23699951171875,
                    "y": -936.6008911132813,
                    "z": 1380.7894287109375
                }
            }
        },
        {
            "orientation": {
                "v": [
                    0.7909536957740784,
                    0.24599315226078033,
                    0.5587114691734314,
                    -0.04148615524172783
                ],
                "wxyz": {
                    "w": 0.7909536957740784,
                    "x": 0.24599315226078033,
                    "y": 0.5587114691734314,
                    "z": -0.04148615524172783
                }
            },
            "position": {
                "v": [
                    -80.228759765625,
                    -928.221435546875,
                    1454.7852783203125
                ],
                "xyz": {
                    "x": -80.228759765625,
                    "y": -928.221435546875,
                    "z": 1454.7852783203125
                }
            }
        },
        {
            "orientation": {
                "v": [
                    -0.1094789206981659,
                    0.2121179848909378,
                    0.8058210611343384,
                    -0.541915774345398
                ],
                "wxyz": {
                    "w": -0.1094789206981659,
                    "x": 0.2121179848909378,
                    "y": 0.8058210611343384,
                    "z": -0.541915774345398
                }
            },
            "position": {
                "v": [
                    -5.4171271324157715,
                    -667.8086547851563,
                    1488.7794189453125
                ],
                "xyz": {
                    "x": -5.4171271324157715,
                    "y": -667.8086547851563,
                    "z": 1488.7794189453125
                }
            }
        },
        {
            "orientation": {
                "v": [
                    0.14979194104671478,
                    0.2762860953807831,
                    0.9481826424598694,
                    -0.046669118106365204
                ],
                "wxyz": {
                    "w": 0.14979194104671478,
                    "x": 0.2762860953807831,
                    "y": 0.9481826424598694,
                    "z": -0.046669118106365204
                }
            },
            "position": {
                "v": [
                    118.38488006591797,
                    -732.154052734375,
                    1496.2490234375
                ],
                "xyz": {
                    "x": 118.38488006591797,
                    "y": -732.154052734375,
                    "z": 1496.2490234375
                }
            }
        },
        {
            "orientation": {
                "v": [
                    0.11984632909297943,
                    0.9481298327445984,
                    0.27646732330322266,
                    0.10125459730625153
                ],
                "wxyz": {
                    "w": 0.11984632909297943,
                    "x": 0.9481298327445984,
                    "y": 0.27646732330322266,
                    "z": 0.10125459730625153
                }
            },
            "position": {
                "v": [
                    358.4462890625,
                    -884.7120971679688,
                    1588.9427490234375
                ],
                "xyz": {
                    "x": 358.4462890625,
                    "y": -884.7120971679688,
                    "z": 1588.9427490234375
                }
            }
        },
        {
            "orientation": {
                "v": [
                    0.7990773916244507,
                    -0.3908673822879791,
                    0.25044816732406616,
                    0.3820651173591614
                ],
                "wxyz": {
                    "w": 0.7990773916244507,
                    "x": -0.3908673822879791,
                    "y": 0.25044816732406616,
                    "z": 0.3820651173591614
                }
            },
            "position": {
                "v": [
                    152.16712951660156,
                    -1021.5924682617188,
                    1557.565673828125
                ],
                "xyz": {
                    "x": 152.16712951660156,
                    "y": -1021.5924682617188,
                    "z": 1557.565673828125
                }
            }
        },
        {
            "orientation": {
                "v": [
                    0.7937087416648865,
                    -0.4382612705230713,
                    -0.15306411683559418,
                    -0.39309659600257874
                ],
                "wxyz": {
                    "w": 0.7937087416648865,
                    "x": -0.4382612705230713,
                    "y": -0.15306411683559418,
                    "z": -0.39309659600257874
                }
            },
            "position": {
                "v": [
                    93.67945861816406,
                    -1074.7464599609375,
                    1634.3011474609375
                ],
                "xyz": {
                    "x": 93.67945861816406,
                    "y": -1074.7464599609375,
                    "z": 1634.3011474609375
                }
            }
        },
        {
            "orientation": {
                "v": [
                    0.7937087416648865,
                    -0.4382612705230713,
                    -0.15306411683559418,
                    -0.39309659600257874
                ],
                "wxyz": {
                    "w": 0.7937087416648865,
                    "x": -0.4382612705230713,
                    "y": -0.15306411683559418,
                    "z": -0.39309659600257874
                }
            },
            "position": {
                "v": [
                    20.99715232849121,
                    -1019.4703369140625,
                    1568.0010986328125
                ],
                "xyz": {
                    "x": 20.99715232849121,
                    "y": -1019.4703369140625,
                    "z": 1568.0010986328125
                }
            }
        },
        {
            "orientation": {
                "v": [
                    0.781158983707428,
                    0.4975902736186981,
                    -0.08951493352651596,
                    -0.36630815267562866
                ],
                "wxyz": {
                    "w": 0.781158983707428,
                    "x": 0.4975902736186981,
                    "y": -0.08951493352651596,
                    "z": -0.36630815267562866
                }
            },
            "position": {
                "v": [
                    25.759138107299805,
                    -985.6563110351563,
                    1553.6025390625
                ],
                "xyz": {
                    "x": 25.759138107299805,
                    "y": -985.6563110351563,
                    "z": 1553.6025390625
                }
            }
        },
        {
            "orientation": {
                "v": [
                    0.40270453691482544,
                    0.5836905241012573,
                    -0.49499914050102234,
                    -0.5021058917045593
                ],
                "wxyz": {
                    "w": 0.40270453691482544,
                    "x": 0.5836905241012573,
                    "y": -0.49499914050102234,
                    "z": -0.5021058917045593
                }
            },
            "position": {
                "v": [
                    -123.60856628417969,
                    -160.2666778564453,
                    1641.3284912109375
                ],
                "xyz": {
                    "x": -123.60856628417969,
                    "y": -160.2666778564453,
                    "z": 1641.3284912109375
                }
            }
        },
        {
            "orientation": {
                "v": [
                    0.43688061833381653,
                    0.5475210547447205,
                    -0.5347239375114441,
                    -0.4726799726486206
                ],
                "wxyz": {
                    "w": 0.43688061833381653,
                    "x": 0.5475210547447205,
                    "y": -0.5347239375114441,
                    "z": -0.4726799726486206
                }
            },
            "position": {
                "v": [
                    -126.04627227783203,
                    257.5260314941406,
                    1721.0679931640625
                ],
                "xyz": {
                    "x": -126.04627227783203,
                    "y": 257.5260314941406,
                    "z": 1721.0679931640625
                }
            }
        },
        {
            "orientation": {
                "v": [
                    0.48911410570144653,
                    0.5096421241760254,
                    -0.5001093149185181,
                    -0.5009222030639648
                ],
                "wxyz": {
                    "w": 0.48911410570144653,
                    "x": 0.5096421241760254,
                    "y": -0.5001093149185181,
                    "z": -0.5009222030639648
                }
            },
            "position": {
                "v": [
                    -118.43991088867188,
                    663.4332885742188,
                    1741.5487060546875
                ],
                "xyz": {
                    "x": -118.43991088867188,
                    "y": 663.4332885742188,
                    "z": 1741.5487060546875
                }
            }
        },
        {
            "orientation": {
                "v": [
                    0.6959805488586426,
                    0.009039302356541157,
                    -0.7179245948791504,
                    -0.01066172868013382
                ],
                "wxyz": {
                    "w": 0.6959805488586426,
                    "x": 0.009039302356541157,
                    "y": -0.7179245948791504,
                    "z": -0.01066172868013382
                }
            },
            "position": {
                "v": [
                    -121.47001647949219,
                    780.2139892578125,
                    1902.701904296875
                ],
                "xyz": {
                    "x": -121.47001647949219,
                    "y": 780.2139892578125,
                    "z": 1902.701904296875
                }
            }
        },
        {
            "orientation": {
                "v": [
                    0.5233509540557861,
                    -0.4690292775630951,
                    -0.552001416683197,
                    0.44878700375556946
                ],
                "wxyz": {
                    "w": 0.5233509540557861,
                    "x": -0.4690292775630951,
                    "y": -0.552001416683197,
                    "z": 0.44878700375556946
                }
            },
            "position": {
                "v": [
                    59.76308822631836,
                    -168.370361328125,
                    1657.2042236328125
                ],
                "xyz": {
                    "x": 59.76308822631836,
                    "y": -168.370361328125,
                    "z": 1657.2042236328125
                }
            }
        },
        {
            "orientation": {
                "v": [
                    0.5041627883911133,
                    -0.49153512716293335,
                    -0.5320794582366943,
                    0.47021743655204773
                ],
                "wxyz": {
                    "w": 0.5041627883911133,
                    "x": -0.49153512716293335,
                    "y": -0.5320794582366943,
                    "z": 0.47021743655204773
                }
            },
            "position": {
                "v": [
                    54.566524505615234,
                    251.22564697265625,
                    1723.82275390625
                ],
                "xyz": {
                    "x": 54.566524505615234,
                    "y": 251.22564697265625,
                    "z": 1723.82275390625
                }
            }
        },
        {
            "orientation": {
                "v": [
                    -0.4630592167377472,
                    0.5416625142097473,
                    0.5492586493492126,
                    -0.4364546537399292
                ],
                "wxyz": {
                    "w": -0.4630592167377472,
                    "x": 0.5416625142097473,
                    "y": 0.5492586493492126,
                    "z": -0.4364546537399292
                }
            },
            "position": {
                "v": [
                    51.10531234741211,
                    660.8480224609375,
                    1754.323486328125
                ],
                "xyz": {
                    "x": 51.10531234741211,
                    "y": 660.8480224609375,
                    "z": 1754.323486328125
                }
            }
        },
        {
            "orientation": {
                "v": [
                    -0.021383725106716156,
                    0.7676239609718323,
                    0.008601799607276917,
                    -0.6404858827590942
                ],
                "wxyz": {
                    "w": -0.021383725106716156,
                    "x": 0.7676239609718323,
                    "y": 0.008601799607276917,
                    "z": -0.6404858827590942
                }
            },
            "position": {
                "v": [
                    25.377912521362305,
                    765.4822998046875,
                    1902.396484375
                ],
                "xyz": {
                    "x": 25.377912521362305,
                    "y": 765.4822998046875,
                    "z": 1902.396484375
                }
            }
        },
        {
            "orientation": {
                "v": [
                    0.12037686258554459,
                    0.6163143515586853,
                    -0.5542877316474915,
                    -0.5462885499000549
                ],
                "wxyz": {
                    "w": 0.12037686258554459,
                    "x": 0.6163143515586853,
                    "y": -0.5542877316474915,
                    "z": -0.5462885499000549
                }
            },
            "position": {
                "v": [
                    -46.08180236816406,
                    -780.5569458007813,
                    1438.47509765625
                ],
                "xyz": {
                    "x": -46.08180236816406,
                    "y": -780.5569458007813,
                    "z": 1438.47509765625
                }
            }
        },
        {
            "orientation": {
                "v": [
                    0.12037686258554459,
                    0.6163143515586853,
                    -0.5542877316474915,
                    -0.5462885499000549
                ],
                "wxyz": {
                    "w": 0.12037686258554459,
                    "x": 0.6163143515586853,
                    "y": -0.5542877316474915,
                    "z": -0.5462885499000549
                }
            },
            "position": {
                "v": [
                    -142.44076538085938,
                    -885.2423706054688,
                    1532.8326416015625
                ],
                "xyz": {
                    "x": -142.44076538085938,
                    "y": -885.2423706054688,
                    "z": 1532.8326416015625
                }
            }
        },
        {
            "orientation": {
                "v": [
                    -0.47140365839004517,
                    -0.043859489262104034,
                    0.8277406096458435,
                    0.30116507411003113
                ],
                "wxyz": {
                    "w": -0.47140365839004517,
                    "x": -0.043859489262104034,
                    "y": 0.8277406096458435,
                    "z": 0.30116507411003113
                }
            },
            "position": {
                "v": [
                    -149.57423400878906,
                    -887.6337890625,
                    1473.8421630859375
                ],
                "xyz": {
                    "x": -149.57423400878906,
                    "y": -887.6337890625,
                    "z": 1473.8421630859375
                }
            }
        },
        {
            "orientation": {
                "v": [
                    0.5462885499000549,
                    -0.5542877316474915,
                    -0.6163143515586853,
                    0.12037687748670578
                ],
                "wxyz": {
                    "w": 0.5462885499000549,
                    "x": -0.5542877316474915,
                    "y": -0.6163143515586853,
                    "z": 0.12037687748670578
                }
            },
            "position": {
                "v": [
                    -132.85877990722656,
                    -801.2422485351563,
                    1371.86865234375
                ],
                "xyz": {
                    "x": -132.85877990722656,
                    "y": -801.2422485351563,
                    "z": 1371.86865234375
                }
            }
        },
        {
            "orientation": {
                "v": [
                    -0.47140365839004517,
                    -0.043859489262104034,
                    0.8277406096458435,
                    0.30116507411003113
                ],
                "wxyz": {
                    "w": -0.47140365839004517,
                    "x": -0.043859489262104034,
                    "y": 0.8277406096458435,
                    "z": 0.30116507411003113
                }
            },
            "position": {
                "v": [
                    -105.8543472290039,
                    -909.8038940429688,
                    1499.97265625
                ],
                "xyz": {
                    "x": -105.8543472290039,
                    "y": -909.8038940429688,
                    "z": 1499.97265625
                }
            }
        },
        {
            "orientation": {
                "v": [
                    0.12037686258554459,
                    0.6163143515586853,
                    -0.5542877316474915,
                    -0.5462885499000549
                ],
                "wxyz": {
                    "w": 0.12037686258554459,
                    "x": 0.6163143515586853,
                    "y": -0.5542877316474915,
                    "z": -0.5462885499000549
                }
            },
            "position": {
                "v": [
                    13.2503662109375,
                    -875.77392578125,
                    1436.4586181640625
                ],
                "xyz": {
                    "x": 13.2503662109375,
                    "y": -875.77392578125,
                    "z": 1436.4586181640625
                }
            }
        }
    ],
    "timestamp": "2022-06-21T13-03-21"
}
